AUTHORS.rst
CONTRIBUTING.rst
HISTORY.rst
LICENSE
MANIFEST.in
README.rst
setup.cfg
setup.py
docs/Makefile
docs/authors.rst
docs/conf.py
docs/contributing.rst
docs/history.rst
docs/index.rst
docs/installation.rst
docs/make.bat
docs/_build/html/_images/fernlab_logo.png
docs/_build/html/_images/jupyter_notebooks_attenuation_correction_12_0.png
docs/_build/html/_images/jupyter_notebooks_attenuation_correction_18_0.png
docs/_build/html/_images/jupyter_notebooks_clutter_detection_18_0.png
docs/_build/html/_images/jupyter_notebooks_clutter_detection_24_0.png
docs/_build/html/_images/jupyter_notebooks_clutter_detection_27_0.png
docs/_build/html/_images/jupyter_notebooks_clutter_detection_6_1.png
docs/_build/html/_images/jupyter_notebooks_geometry_module_13_1.png
docs/_build/html/_images/jupyter_notebooks_precipitation_estimation_7_1.png
docs/_build/html/_images/jupyter_notebooks_read_furuno_data_31_1.png
docs/_build/html/_images/jupyter_notebooks_read_furuno_data_34_1.png
docs/_build/html/_static/file.png
docs/_build/html/_static/minus.png
docs/_build/html/_static/plus.png
docs/_build/html/_static/wrainfo_logo.png
docs/images/fernlab_logo.png
docs/images/wr_furuno_comparison_of_raw_reflectivity_and_clutter_corrected_reflectivity.png
docs/images/wr_furuno_georeferenced_and_gridded_precipitation_data_with_WRaINfo.png
docs/images/wr_furuno_reflectivity_attenaution_corrected_and_estimated_precipitation.png
docs/images/wr_furuno_reflectivity_before_and_after_attenaution_correction.png
docs/images/wrainfo_logo.png
docs/process_chains/clutter_chain.rst
docs/process_chains/introduction.rst
docs/process_chains/static_cmap.rst
docs/process_chains/wr_routine_furuno_level2a.rst
docs/tutorials_and_examples/attenuation_correction_module.rst
docs/tutorials_and_examples/clutter_detection_module.rst
docs/tutorials_and_examples/data_input.rst
docs/tutorials_and_examples/features_overview.rst
docs/tutorials_and_examples/further_features.rst
docs/tutorials_and_examples/geometry_module.rst
wrainfo.egg-info/PKG-INFO
wrainfo.egg-info/SOURCES.txt
wrainfo.egg-info/dependency_links.txt
wrainfo.egg-info/entry_points.txt
wrainfo.egg-info/not-zip-safe
wrainfo.egg-info/requires.txt
wrainfo.egg-info/top_level.txt