Metadata-Version: 2.1
Name: wrainfo
Version: 0.9.5
Summary: Is a software to process FURUNO weather radar data.
Home-page: https://git.gfz-potsdam.de/fernlab/products/furuno/wrainfo
Author: FernLab
Author-email: fernlab@gfz-potsdam.de
License: Apache Software License 2.0
Project-URL: Source code, https://git.gfz-potsdam.de/fernlab/products/furuno/wrainfo
Project-URL: Documentation, https://fernlab.git-pages.gfz-potsdam.de/products/furuno/wrainfo/doc/
Project-URL: Change log, https://git.gfz-potsdam.de/fernlab/products/furuno/wrainfo/-/blob/main/HISTORY.rst
Keywords: wrainfo,weather radar,X-Band,preprocessing,clutter detection,attenuation correction,precipitation estimation
Classifier: Development Status :: 2 - Pre-Alpha
Classifier: Intended Audience :: Developers
Classifier: License :: OSI Approved :: Apache Software License
Classifier: Natural Language :: English
Classifier: Programming Language :: Python :: 3
Classifier: Programming Language :: Python :: 3.7
Classifier: Programming Language :: Python :: 3.8
Classifier: Programming Language :: Python :: 3.9
Classifier: Programming Language :: Python :: 3.10
Requires-Python: >=3.7
Provides-Extra: doc
Provides-Extra: test
Provides-Extra: lint
Provides-Extra: dev
License-File: LICENSE
License-File: AUTHORS.rst
